llama_index/readers/docling/__init__.py
llama_index/readers/docling/base.py
llama_index_readers_docling-0.4.1.dist-info/METADATA
llama_index_readers_docling-0.4.1.dist-info/WHEEL
llama_index_readers_docling-0.4.1.dist-info/licenses/LICENSE
llama_index_readers_docling-0.4.1.dist-info/RECORD
