Metadata-Version: 2.4
Name: llama-index-readers-docling
Version: 0.4.1
Summary: llama-index readers docling integration
Author-email: Panos Vagenas <pva@zurich.ibm.com>
License-Expression: MIT
License-File: LICENSE
Requires-Python: <3.13,>=3.10
Requires-Dist: docling-core<3,>=2.2.0
Requires-Dist: docling<3,>=2.2.0
Requires-Dist: llama-index-core<0.15,>=0.13.0
Requires-Dist: numpy>=2.0
